doctr_versions_menu/__init__.py
doctr_versions_menu/cli.py
doctr_versions_menu/click_config_file.py
doctr_versions_menu/ext.py
doctr_versions_menu/folder_spec.py
doctr_versions_menu/groups.py
doctr_versions_menu/version_data.py
doctr_versions_menu/_css/badge_only.css
doctr_versions_menu/_fonts/fontawesome-webfont.eot
doctr_versions_menu/_fonts/fontawesome-webfont.svg
doctr_versions_menu/_fonts/fontawesome-webfont.ttf
doctr_versions_menu/_fonts/fontawesome-webfont.woff
doctr_versions_menu/_fonts/fontawesome-webfont.woff2
doctr_versions_menu/_script/versions.py
doctr_versions_menu/_template/doctr-versions-menu.js_t
doctr_versions_menu/_template/index.html_t
doctr_versions_menu-0.4.1.dist-info/LICENSE
doctr_versions_menu-0.4.1.dist-info/METADATA
doctr_versions_menu-0.4.1.dist-info/WHEEL
doctr_versions_menu-0.4.1.dist-info/entry_points.txt
doctr_versions_menu-0.4.1.dist-info/top_level.txt
doctr_versions_menu-0.4.1.dist-info/RECORD
