Metadata-Version: 2.1
Name: doctr-versions-menu
Version: 0.4.1
Summary: Sphinx extension and command to add a versions menu to Doctr-deployed documentation
Home-page: https://github.com/goerz/doctr_versions_menu
Author: Michael Goerz
Author-email: mail@michaelgoerz.net
License: MIT license
Keywords: Doctr,Sphinx,Github
Platform: UNKNOWN
Classifier: Development Status :: 4 - Beta
Classifier: Intended Audience :: Developers
Classifier: License :: OSI Approved :: MIT License
Classifier: Natural Language :: English
Classifier: Environment :: Console
Classifier: Environment :: Web Environment
Classifier: Environment :: Plugins
Classifier: Framework :: Sphinx
Classifier: Framework :: Sphinx :: Extension
Classifier: Operating System :: OS Independent
Classifier: Topic :: Documentation
Classifier: Topic :: Documentation :: Sphinx
Classifier: Topic :: Software Development :: Documentation
Classifier: Topic :: Utilities
Classifier: Programming Language :: JavaScript
Classifier: Programming Language :: Python :: 3 :: Only
Classifier: Programming Language :: Python :: 3.5
Classifier: Programming Language :: Python :: 3.6
Classifier: Programming Language :: Python :: 3.7
Classifier: Programming Language :: Python :: 3.8
Classifier: Programming Language :: Python :: 3.9
Requires-Python: >=3.5
Requires-Dist: click (>=6.7)
Requires-Dist: configobj (>=5.0.6)
Requires-Dist: doctr
Requires-Dist: packaging
Requires-Dist: pyparsing (>=2.0.2)
Requires-Dist: setuptools
Requires-Dist: sphinx
Provides-Extra: dev
Requires-Dist: coverage ; extra == 'dev'
Requires-Dist: coveralls ; extra == 'dev'
Requires-Dist: flake8 ; extra == 'dev'
Requires-Dist: gitpython ; extra == 'dev'
Requires-Dist: ipython ; extra == 'dev'
Requires-Dist: isort ; extra == 'dev'
Requires-Dist: pdbpp ; extra == 'dev'
Requires-Dist: pre-commit ; extra == 'dev'
Requires-Dist: pylint ; extra == 'dev'
Requires-Dist: pytest ; extra == 'dev'
Requires-Dist: pytest-cov ; extra == 'dev'
Requires-Dist: pytest-xdist ; extra == 'dev'
Requires-Dist: sphinx ; extra == 'dev'
Requires-Dist: sphinx-autobuild ; extra == 'dev'
Requires-Dist: sphinx-autodoc-typehints ; extra == 'dev'
Requires-Dist: sphinx-copybutton ; extra == 'dev'
Requires-Dist: sphinx-rtd-theme ; extra == 'dev'
Requires-Dist: travis-encrypt ; extra == 'dev'
Requires-Dist: twine ; extra == 'dev'
Requires-Dist: wheel ; extra == 'dev'
Requires-Dist: black ; extra == 'dev'
